django_subdomain_middleware/__init__.py
django_subdomain_middleware/subdomain.py
Django_Subdomain_Middleware-4.2.0.dist-info/LICENSE
Django_Subdomain_Middleware-4.2.0.dist-info/METADATA
Django_Subdomain_Middleware-4.2.0.dist-info/WHEEL
Django_Subdomain_Middleware-4.2.0.dist-info/top_level.txt
Django_Subdomain_Middleware-4.2.0.dist-info/RECORD
