Metadata-Version: 2.1
Name: Django-Subdomain-Middleware
Version: 4.2.0
Summary: Django middleware to handle routing for subdomains.
Home-page: https://github.com/RockProfile/django-subdomain-middleware
Author: Peter McDonald
Author-email: git@petermcdonald.co.uk
Project-URL: Bug Tracker, https://github.com/RockProfile/django-subdomain-middleware/issues
Project-URL: Source, https://github.com/RockProfile/django-subdomain-middleware
Classifier: Programming Language :: Python :: 3.8
Classifier: Programming Language :: Python :: 3.9
Classifier: Programming Language :: Python :: 3.10
Classifier: Programming Language :: Python :: 3.11
Classifier: License :: OSI Approved :: MIT License
Classifier: Operating System :: OS Independent
Classifier: Intended Audience :: Developers
Requires-Python: >=3.8
License-File: LICENSE
Requires-Dist: Django (<5,>=4.2)
Provides-Extra: build
Requires-Dist: wheel ; extra == 'build'
Requires-Dist: build ; extra == 'build'
